azdevops_cli-0.3.2.data/scripts/azdevops
src/__init__.py
src/cli.py
src/base/__init__.py
src/base/commands/__init__.py
src/base/commands/cli/__init__.py
src/base/commands/cli/cli_command.py
src/base/commands/cli/version_command.py
src/exceptions/__init__.py
src/exceptions/azdevops_api_exception.py
src/exceptions/azdevops_exception.py
src/helpers/__init__.py
src/helpers/azure_devops.py
src/helpers/logger.py
src/helpers/tests/__init__.py
src/helpers/tests/test_azure_devops.py
src/models/__init__.py
src/models/azure_devops_credentials.py
src/models/azure_devops_definition.py
src/models/helper.py
src/models/release_summary.py
src/models/version_infos.py
src/release_manager/__init__.py
src/release_manager/cli.py
src/release_manager/commands/__init__.py
src/release_manager/commands/cli/__init__.py
src/release_manager/commands/cli/changelog_command.py
src/release_manager/commands/cli/manifest_command.py
src/release_manager/commands/cli/summary_command.py
src/release_manager/exceptions/__init__.py
src/release_manager/exceptions/release_manager_exception.py
src/release_manager/helpers/__init__.py
src/release_manager/helpers/changelog_generator.py
src/release_manager/helpers/manifest_generator.py
src/release_manager/helpers/os_util.py
src/release_manager/helpers/summary_generator.py
src/release_manager/tests/__init__.py
src/release_manager/tests/commands/__init__.py
src/release_manager/tests/commands/cli/__init__.py
src/release_manager/tests/commands/cli/test_manifest_command.py
src/release_manager/tests/helpers/__init__.py
src/release_manager/tests/helpers/test_os_util.py
src/repo_updater/__init__.py
src/repo_updater/cli.py
src/repo_updater/schema.py
src/repo_updater/commands/__init__.py
src/repo_updater/commands/cli/__init__.py
src/repo_updater/commands/cli/run_command.py
src/repo_updater/commands/files/__init__.py
src/repo_updater/commands/files/add_file_command.py
src/repo_updater/commands/files/delete_file_command.py
src/repo_updater/commands/files/file_command.py
azdevops_cli-0.3.2.dist-info/LICENSE
azdevops_cli-0.3.2.dist-info/METADATA
azdevops_cli-0.3.2.dist-info/WHEEL
azdevops_cli-0.3.2.dist-info/top_level.txt
azdevops_cli-0.3.2.dist-info/RECORD
