Metadata-Version: 2.1
Name: azdevops-cli
Version: 0.3.2
Summary: An Azure DevOps cli tool
Author: Gwendall Garnier, Damien Aicheh
Project-URL: Homepage, https://github.com/damienaicheh/azdevops-cli
Project-URL: Bug Tracker, https://github.com/damienaicheh/azdevops-cli/issues
Classifier: Programming Language :: Python :: 3.8
Classifier: License :: OSI Approved :: MIT License
Classifier: Operating System :: OS Independent
Requires-Python: >=3.8
License-File: LICENSE
Requires-Dist: Cerberus (==1.3.4)
Requires-Dist: certifi (==2022.9.24)
Requires-Dist: charset-normalizer (==2.1.1)
Requires-Dist: click (==8.1.3)
Requires-Dist: coverage (==6.5.0)
Requires-Dist: gitdb (==4.0.9)
Requires-Dist: GitPython (==3.1.29)
Requires-Dist: idna (==3.4)
Requires-Dist: isodate (==0.6.1)
Requires-Dist: msrest (==0.6.21)
Requires-Dist: oauthlib (==3.2.2)
Requires-Dist: PyYAML (==6.0)
Requires-Dist: python-dateutil (==2.8.2)
Requires-Dist: requests (==2.28.1)
Requires-Dist: requests-oauthlib (==1.3.1)
Requires-Dist: six (==1.16.0)
Requires-Dist: smmap (==5.0.0)
Requires-Dist: urllib3 (==1.26.12)
